classic/cache/__init__.py
classic/cache/cache.py
classic/cache/decorator.py
classic/cache/key_generator.py
classic/cache/caches/__init__.py
classic/cache/caches/in_memory.py
classic/cache/caches/redis.py
classic/cache/key_generators/__init__.py
classic/cache/key_generators/blake2b.py
classic/cache/key_generators/msgspec.py
classic/cache/key_generators/orjson.py
classic/cache/key_generators/pure_hash.py
classic_cache-1.2.1.dist-info/licenses/LICENSE
classic_cache-1.2.1.dist-info/METADATA
classic_cache-1.2.1.dist-info/WHEEL
classic_cache-1.2.1.dist-info/top_level.txt
classic_cache-1.2.1.dist-info/RECORD
