Metadata-Version: 2.4
Name: classic-cache
Version: 1.2.1
Summary: Provides cache utils
Author-email: Sergey Variasov <variasov@gmail.com>
Project-URL: Homepage, https://github.com/variasov/classic-cache
Requires-Python: >=3.10
License-File: LICENSE
Requires-Dist: classic-components~=1.3
Requires-Dist: orjson~=3.10
Requires-Dist: msgspec~=0.18
Provides-Extra: dev
Requires-Dist: build~=1.2.2.post1; extra == "dev"
Requires-Dist: pytest==8.3.4; extra == "dev"
Requires-Dist: pytest-cov==6.0.0; extra == "dev"
Requires-Dist: twine~=4.0; extra == "dev"
Requires-Dist: fakeredis==2.24.1; extra == "dev"
Requires-Dist: freezegun==1.5.1; extra == "dev"
Provides-Extra: redis
Requires-Dist: redis==5.0.8; extra == "redis"
Dynamic: license-file
